pconfig/__init__.py
pconfig/config.py
pconfig/config_value.py
pconfig/error.py
pconfig/notset.py
pconfig/loaders/__init__.py
pconfig/loaders/dotenv_loader.py
pconfig/loaders/envvar_loader.py
pconfig/loaders/loader.py
pconfig/loaders/yaml_loader.py
polidoro_config-1.0.1.dist-info/LICENSE
polidoro_config-1.0.1.dist-info/METADATA
polidoro_config-1.0.1.dist-info/WHEEL
polidoro_config-1.0.1.dist-info/top_level.txt
polidoro_config-1.0.1.dist-info/RECORD
