Metadata-Version: 2.1
Name: polidoro-config
Version: 1.0.1
Summary: Package to manage configuration for you project.
Author: Heitor Luis Polidoro
License: MIT
Project-URL: Homepage, https://github.com/heitorpolidoro/polidoro-config
Project-URL: Documentation, https://polidoro-config.readthedocs.io/
Classifier: Programming Language :: Python :: 3.10
Classifier: Programming Language :: Python :: 3.11
Classifier: Programming Language :: Python :: 3.12
Classifier: License :: OSI Approved :: MIT License
Classifier: Operating System :: OS Independent
Requires-Python: >=3.10
License-File: LICENSE
